codeunify/__init__.py
codeunify/core/__init__.py
codeunify/core/combine.py
codeunify/tests/__init__.py
codeunify/tests/test_combine.py
codeunify-0.2.6.dist-info/METADATA
codeunify-0.2.6.dist-info/WHEEL
codeunify-0.2.6.dist-info/entry_points.txt
codeunify-0.2.6.dist-info/top_level.txt
codeunify-0.2.6.dist-info/RECORD
