Metadata-Version: 2.1
Name: codeunify
Version: 0.2.6
Summary: A library to combine multiple code files into one for easier AI context and error analysis
Home-page: https://github.com/takuphilchan/codeunify
Author: Phillip Chananda
Author-email: takuphilchan@gmail.com
Project-URL: Bug Tracker, https://github.com/takuphilchan/codeunify/issues
Project-URL: Documentation, https://github.com/takuphilchan/codeunify#readme
Project-URL: Source Code, https://github.com/takuphilchan/codeunify
Classifier: Development Status :: 3 - Alpha
Classifier: Intended Audience :: Developers
Classifier: Topic :: Software Development :: Libraries :: Python Modules
Classifier: Programming Language :: Python :: 3
Classifier: License :: OSI Approved :: MIT License
Classifier: Operating System :: OS Independent
Requires-Python: >=3.7
Requires-Dist: numpy
